regisoup/__init__.py
regisoup/__main__.py
regisoup/main.py
regisoup-0.1.11.dist-info/METADATA
regisoup-0.1.11.dist-info/WHEEL
regisoup-0.1.11.dist-info/entry_points.txt
regisoup-0.1.11.dist-info/RECORD
