Metadata-Version: 2.1
Name: regisoup
Version: 0.1.11
Summary: Convert <figure> and <xr> tags from deprecated MediaWiki extension to a new supported format.
Author: pengu5055
Author-email: urbancmarko1@gmail.com
Requires-Python: >=3.7,<4.0
Classifier: Programming Language :: Python :: 3
Classifier: Programming Language :: Python :: 3.7
Classifier: Programming Language :: Python :: 3.8
Classifier: Programming Language :: Python :: 3.9
Classifier: Programming Language :: Python :: 3.10
Classifier: Programming Language :: Python :: 3.11
Requires-Dist: beautifulsoup4 (>=4.12.0,<5.0.0)
Requires-Dist: lxml (>=4.9.2,<5.0.0)
Requires-Dist: typer[all] (>=0.7.0,<0.8.0)
